setup.py
kleio/__init__.py
kleio/prov.py
kleio.egg-info/PKG-INFO
kleio.egg-info/SOURCES.txt
kleio.egg-info/dependency_links.txt
kleio.egg-info/requires.txt
kleio.egg-info/top_level.txt
test/test_prov.py