Metadata-Version: 1.1
Name: kleio
Version: 0.2.0
Summary: A simple python implementation of the W3C PROV data model
Home-page: http://github.com/tetherless-world/kleio
Author: Stephan Zednik
Author-email: zednis2@rpi.edu
License: MIT
Keywords: provenance PROV PROV-O rdf
Platform: UNKNOWN
Classifier: Development Status :: 4 - Beta
Classifier: License :: OSI Approved :: MIT License
Classifier: Programming Language :: Python :: 3
